README.md
cleanslate/setup.py
cleanslate.egg-info/PKG-INFO
cleanslate.egg-info/SOURCES.txt
cleanslate.egg-info/dependency_links.txt
cleanslate.egg-info/not-zip-safe
cleanslate.egg-info/top_level.txt