Metadata-Version: 1.0
Name: cleanslate
Version: 0.23
Summary: Say Goodbye to browser history as you always wanted i.e selectively removing the browsing history
Home-page: http://github.com/prdpx7/CleanSlate
Author: Pradeep Khileri
Author-email: pradeepchoudhary009@gmail.com
License: MIT
Platform: UNKNOWN
